README.md
setup.py
flachemy_session/__init__.py
flachemy_session.egg-info/PKG-INFO
flachemy_session.egg-info/SOURCES.txt
flachemy_session.egg-info/dependency_links.txt
flachemy_session.egg-info/requires.txt
flachemy_session.egg-info/top_level.txt