Metadata-Version: 1.1
Name: flachemy-session
Version: 0.0.3
Summary: Ease to handle sqlalchemy session with flask.
Home-page: UNKNOWN
Author: kinpira
Author-email: ksk.uchi+flachemy-session@gmail.com
License: MIT
Platform: UNKNOWN
Classifier: Programming Language :: Python :: 3
Classifier: Programming Language :: Python :: 3.5
Classifier: Programming Language :: Python :: 3.6
Classifier: License :: OSI Approved :: MIT License
